projectpro/__init__.py
projectpro/checkpoint.py
projectpro/utils.py
projectpro-0.0.30.dist-info/METADATA
projectpro-0.0.30.dist-info/WHEEL
projectpro-0.0.30.dist-info/top_level.txt
projectpro-0.0.30.dist-info/RECORD
