Metadata-Version: 2.1
Name: projectpro
Version: 0.0.30
Summary: Code execution logging
Author: ProjectPro
Author-email: mohammed@projectpro.io
Keywords: python,logging,checkpoint,log,script,ipynb
Classifier: Programming Language :: Python :: 3
Classifier: Operating System :: OS Independent
Requires-Dist: requests
Requires-Dist: geocoder
